LICENSE.txt
MANIFEST.in
README.rst
setup.py
bin/boxcar-broadcast.py
bin/boxcar-notify.py
bin/boxcar-subscribe.py
boxcar/__init__.py
boxcar/exc/__init__.py
python_boxcar.egg-info/PKG-INFO
python_boxcar.egg-info/SOURCES.txt
python_boxcar.egg-info/dependency_links.txt
python_boxcar.egg-info/requires.txt
python_boxcar.egg-info/top_level.txt
test/test_boxcar.py