Metadata-Version: 1.0
Name: python-boxcar
Version: 0.1.2
Summary: A Boxcar.io API library.
Home-page: https://github.com/markcaudill/boxcar
Author: Mark Caudill
Author-email: mark@markcaudill.me
License: GPLv3
Keywords: boxcar api notify
Platform: UNKNOWN
